decrypt/__init__.py
decrypt/__version__.py
decrypt/decrypt.py
encrypt/__init__.py
encrypt/__version__.py
encrypt/encrypt.py
chnese_encrypt_or_decrypt-0.1.0.dist-info/LICENSE
chnese_encrypt_or_decrypt-0.1.0.dist-info/METADATA
chnese_encrypt_or_decrypt-0.1.0.dist-info/WHEEL
chnese_encrypt_or_decrypt-0.1.0.dist-info/top_level.txt
chnese_encrypt_or_decrypt-0.1.0.dist-info/RECORD
